ngdb/__init__.py
ngdb/dosify.py
ngdb/entry.py
ngdb/guide.py
ngdb/link.py
ngdb/menu.py
ngdb/parser.py
ngdb/prompts.py
ngdb/py.typed
ngdb/reader.py
ngdb/seealso.py
ngdb/types.py
ngdb-1.2.0.dist-info/WHEEL
ngdb-1.2.0.dist-info/METADATA
ngdb-1.2.0.dist-info/RECORD
