Metadata-Version: 2.4
Name: ngdb
Version: 1.2.0
Summary: Norton Guide database reading library
Keywords: library,dbase,clipper,norton guide reader,documentation,database,help
Author: Dave Pearson
Author-email: Dave Pearson <davep@davep.org>
License-Expression: GPL-3.0-or-later
Classifier: Development Status :: 5 - Production/Stable
Classifier: Operating System :: OS Independent
Classifier: Programming Language :: Python :: 3 :: Only
Classifier: Programming Language :: Python :: 3
Classifier: Programming Language :: Python :: 3.10
Classifier: Programming Language :: Python :: 3.11
Classifier: Programming Language :: Python :: 3.12
Classifier: Programming Language :: Python :: 3.13
Classifier: Programming Language :: Python :: 3.14
Classifier: Topic :: Documentation
Classifier: Topic :: Software Development :: Documentation
Classifier: Topic :: Software Development :: Libraries
Classifier: Typing :: Typed
Requires-Dist: typing-extensions
Requires-Python: >=3.10
Project-URL: Discussions, https://github.com/davep/ngdb.py/discussions
Project-URL: Documentation, https://ngdb.davep.dev/
Project-URL: Homepage, https://ngdb.davep.dev/
Project-URL: Issues, https://github.com/davep/ngdb.py/issues
Project-URL: Repository, https://github.com/davep/ngdb.py
Project-URL: Source, https://github.com/davep/ngdb.py
